{
	"id": "demystifying-mlops",
	"title": "Demystifying MLOps: A Practical Guide for Data Scientists",
	"publicationDate": "2024-04-15",
	"author": "Alex Johnson",
	"snippet": "MLOps is more than just a buzzword. It's a crucial set of practices for streamlining the machine learning lifecycle, from experimentation to production. In this post, we explore core principles and practical steps...",
	"content": "<p>MLOps, or Machine Learning Operations, has become increasingly vital in the world of data science. It bridges the gap between model development and deployment, ensuring that machine learning models are not just built, but are also reliably and efficiently brought into production and maintained.</p><h3 class='text-xl font-semibold mt-6 mb-3 text-blue-600 dark:text-blue-400'>Why MLOps Matters in Today's AI Landscape</h3><p>Without MLOps, data science projects often stall at the prototype phase. Models might work well in a Jupyter notebook but fail to deliver consistent value in a real-world environment. MLOps introduces principles from DevOps, such as automation, continuous integration/continuous deployment (CI/CD), and robust monitoring, to the machine learning workflow. This leads to faster iteration, improved model quality, and greater ROI from AI initiatives.</p><h3 class='text-xl font-semibold mt-6 mb-3 text-blue-600 dark:text-blue-400'>Key Components of a Robust MLOps Framework:</h3><ul class='list-disc list-inside ml-4 space-y-2 text-gray-700 dark:text-gray-300'><li><strong>Data Management & Versioning:</strong> Ensuring reproducible experiments by versioning datasets (e.g., DVC), managing data quality, and building automated data pipelines.</li><li><strong>Model Training & Experiment Tracking:</strong> Implementing reproducible training pipelines, systematically tracking experiments (e.g., MLflow, Weights & Biases), and automating hyperparameter optimization.</li><li><strong>Model Deployment & Serving:</strong> Choosing appropriate deployment strategies (e.g., REST APIs, batch prediction, edge deployment), implementing CI/CD for models, and versioning deployed models.</li><li><strong>Model Monitoring & Retraining:</strong> Continuously tracking model performance in production, detecting data drift and concept drift, and establishing automated retraining triggers.</li><li><strong>Collaboration & Governance:</strong> Utilizing tools and processes for effective collaboration between data scientists, ML engineers, software engineers, and business stakeholders. Implementing model governance and ensuring regulatory compliance.</li></ul><p class='mt-6 text-gray-700 dark:text-gray-300'>Implementing MLOps can seem daunting, but starting with small, incremental improvements can make a significant difference. Tools like Kubeflow, MLflow, and cloud-based solutions from AWS (SageMaker MLOps), Google Cloud (Vertex AI), and Azure (Azure Machine Learning) offer powerful capabilities to support your MLOps journey. The key is to adopt a mindset of continuous improvement and automation throughout the ML lifecycle.</p>",
	"tags": [ "MLOps", "Machine Learning", "Best Practices", "Deployment", "AI Operations" ]
}
